setup.py
redis_client/__init__.py
sca_redis_python.egg-info/PKG-INFO
sca_redis_python.egg-info/SOURCES.txt
sca_redis_python.egg-info/dependency_links.txt
sca_redis_python.egg-info/not-zip-safe
sca_redis_python.egg-info/requires.txt
sca_redis_python.egg-info/top_level.txt