Metadata-Version: 1.1
Name: sca-redis-python
Version: 1.1
Summary: Provides a redis client, more specific to work with AWS Lambda
Home-page: https://github.com/Tesla-SCA/sca_redis_python
Author: Venkatesh Kara, Sona Allahverdiyeva
Author-email: vkara@tesla.com
License: UNKNOWN
Platform: UNKNOWN
Classifier: Programming Language :: Python :: 3.6
